{
    "manufacturer": "yushakobo",
    "keyboard_name": "Quick Paint",
    "maintainer": "yushakobo",
    "bootloader": "rp2040",
    "dynamic_keymap": {
        "layer_count": 4
    },
    "encoder": {
        "enabled": true,
        "rotary": [
            {"pin_a": "GP12", "pin_b": "GP13"}
        ]
    },
    "features": {
        "bootmagic": true,
        "command": false,
        "console": false,
        "encoder": true,
        "encoder_map": true,
        "extrakey": true,
        "mousekey": true,
        "nkro": true,
        "rgblight": true,
        "rgb_matrix": false,
        "via": true
    },
    "matrix_pins": {
        "direct": [
            [28, 27, 26, 25, 11],
            [24, 23, 22, 21, null],
            [20, 19, 18, 17, null]
        ]
    },
    "processor": "RP2040",
    "rgblight": {
        "animations": {
            "breathing": true,
            "rainbow_mood": true,
            "rainbow_swirl": true,
            "snake": true,
            "knight": true,
            "christmas": true,
            "static_gradient": true,
            "rgb_test": true,
            "alternating": true
        },
        "led_count": 12,
    },
    "rgb_matrix": {
        "animations": {
          "alpha_mods": true,
          "gradient_up_down": true,
          "breathing": true,
          "band_sat": true,
          "band_val": true,
          "band_pinwheel_sat": true,
          "band_pinwheel_val": true,
          "band_spiral_sat": true,
          "band_spiral_val": true,
          "cycle_all": true,
          "cycle_left_right": true,
          "cycle_out_in": true,
          "cycle_out_in_dual": true,
          "rainbow_moving_chevron": true,
          "cycle_pinwheel": true,
          "cycle_spiral": true,
          "dual_beacon": true,
          "rainbow_beacon": true,
          "rainbow_pinwheels": true,
          "raindrops": true,
          "jellybean_raindrops": true,
          "typing_heatmap": true,
        },
        "center_point": [112, 32],
        "driver": "ws2812",
        "layout":[
          {"matrix": [0, 3], "x": 0, "y": 0, "flags": 4},
          {"matrix": [0, 2], "x": 75, "y": 0, "flags": 4},
          {"matrix": [0, 1], "x": 149, "y": 0, "flags": 4},
          {"matrix": [0, 0], "x": 224, "y": 0, "flags": 4},
          {"matrix": [1, 0], "x": 0, "y": 32, "flags": 4},
          {"matrix": [1, 1], "x": 75, "y": 32, "flags": 4},
          {"matrix": [1, 2], "x": 149, "y": 32, "flags": 4},
          {"matrix": [1, 3], "x": 224, "y": 32, "flags": 4},
          {"matrix": [2, 3], "x": 0, "y": 64, "flags": 4},
          {"matrix": [2, 2], "x": 75, "y": 64, "flags": 4},
          {"matrix": [2, 1], "x": 149, "y": 64, "flags": 4},
          {"matrix": [2, 0], "x": 224, "y": 64, "flags": 4},
        ]
    },
    "url": "",
    "usb": {
        "device_version": "1.0.0",
        "pid": "0x0009",
        "vid": "0x3265"
    },
    "ws2812": {
        "driver": "vendor",
        "pin": 29
    },
    "layouts": {
        "LAYOUT": {
            "layout": [
                {"matrix": [0, 0], "x": 0, "y": 0},
                {"matrix": [0, 1], "x": 1, "y": 0},
                {"matrix": [0, 2], "x": 2, "y": 0},
                {"matrix": [0, 3], "x": 3, "y": 0},
                {"matrix": [0, 4], "x": 4, "y": 0},
                {"matrix": [1, 0], "x": 0, "y": 1},
                {"matrix": [1, 1], "x": 1, "y": 1},
                {"matrix": [1, 2], "x": 2, "y": 1},
                {"matrix": [1, 3], "x": 3, "y": 1},
                {"matrix": [1, 4], "x": 4, "y": 1},
                {"matrix": [2, 0], "x": 0, "y": 2},
                {"matrix": [2, 1], "x": 1, "y": 2},
                {"matrix": [2, 2], "x": 2, "y": 2},
                {"matrix": [2, 3], "x": 3, "y": 2},
                {"matrix": [2, 4], "x": 4, "y": 2}
            ]
        }
    }
}
